pymagento_rest/__init__.py
pymagento_rest/compare_type.py
pymagento_rest/constants.py
pymagento_rest/filter.py
pymagento_rest/samples/__init__.py
pymagento_rest/samples/products.py
pymagento_rest/v2_2/__init__.py
pymagento_rest/v2_2/api.py
PyMagento_REST-0.3.1.dist-info/LICENSE
PyMagento_REST-0.3.1.dist-info/METADATA
PyMagento_REST-0.3.1.dist-info/WHEEL
PyMagento_REST-0.3.1.dist-info/top_level.txt
PyMagento_REST-0.3.1.dist-info/RECORD
